heal/__init__.py
heal/util.py
heal/watch.py
heal-0.10.1.data/scripts/heald
heal-0.10.1.dist-info/LICENSE
heal-0.10.1.dist-info/METADATA
heal-0.10.1.dist-info/WHEEL
heal-0.10.1.dist-info/top_level.txt
heal-0.10.1.dist-info/RECORD
